{
  "week_start_date": "2026-04-27",
  "generated_at": "2026-04-27T06:00:07.117112+00:00",
  "locality": "seoul",
  "genre": "jazz",
  "highlights": {
    "2026-04-29": {
      "event_id": "evt_20260429_16aecccf-d98a-4622-bc92-d8b0f51e672e",
      "title": {
        "ko": "단예 퀄텟",
        "en": "Dan-ye Quartet"
      },
      "venue_name": {
        "en": "Entry55",
        "ko": "엔트리55"
      },
      "venue_handle": "entry55_official",
      "datetime": "2026-04-29T10:30:00+00:00",
      "selected_at": "2026-04-27T06:00:07.115753+00:00"
    },
    "2026-04-30": {
      "event_id": "evt_20260430_1430e042-a3da-4bfe-b4c4-e273b6f1b18e",
      "title": {
        "ko": "윤찬 트리오",
        "en": "Yun Chan Trio"
      },
      "venue_name": {
        "en": "Oleojazzpub",
        "ko": "올레오재즈펍"
      },
      "venue_handle": "oleojazzpub",
      "datetime": "2026-04-30T11:00:00+00:00",
      "selected_at": "2026-04-27T06:00:07.116123+00:00"
    },
    "2026-05-01": {
      "event_id": "evt_20260501_5a04169d-70e8-4700-a29d-56110d8260c7",
      "title": {
        "ko": "김참치",
        "en": "Tuna Kim"
      },
      "venue_name": {
        "en": "Sounddog",
        "ko": "사운드독"
      },
      "venue_handle": "sounddog_jazz",
      "datetime": "2026-05-01T11:00:00+00:00",
      "selected_at": "2026-04-27T06:00:07.116786+00:00"
    },
    "2026-05-03": {
      "event_id": "evt_20260503_6cba6566-2ffa-4a49-a3b3-b13e4f3e9d02",
      "title": {
        "ko": "김철수 트리오",
        "en": "Kim Cheolsu Trio"
      },
      "venue_name": {
        "en": "FLATNINE",
        "ko": "플랫나인"
      },
      "venue_handle": "flatnine_jazzbar",
      "datetime": "2026-05-03T10:00:00+00:00",
      "selected_at": "2026-04-27T06:00:07.117099+00:00"
    }
  }
}